<?xml version="1.0" encoding="utf-8"?>
<UANodeSet xmlns:xsd="http://www.w3.org/2001/XMLSchema" xmlns:xsi="http://www.w3.org/2001/XMLSchema-instance" xmlns="http://opcfoundation.org/UA/2011/03/UANodeSet.xsd">
  <NamespaceUris>
    <Uri>http://technosoftware.com/ModelDesignServer/Model</Uri>
  </NamespaceUris>
  <Models>
    <Model ModelUri="http://technosoftware.com/ModelDesignServer/Model">
      <RequiredModel ModelUri="http://opcfoundation.org/UA/" Version="1.04.7" PublicationDate="2020-07-15T00:00:00Z" />
    </Model>
  </Models>
  <Aliases>
    <Alias Alias="Boolean">i=1</Alias>
    <Alias Alias="SByte">i=2</Alias>
    <Alias Alias="Byte">i=3</Alias>
    <Alias Alias="Int16">i=4</Alias>
    <Alias Alias="UInt16">i=5</Alias>
    <Alias Alias="Int32">i=6</Alias>
    <Alias Alias="UInt32">i=7</Alias>
    <Alias Alias="Int64">i=8</Alias>
    <Alias Alias="UInt64">i=9</Alias>
    <Alias Alias="Float">i=10</Alias>
    <Alias Alias="Double">i=11</Alias>
    <Alias Alias="DateTime">i=13</Alias>
    <Alias Alias="String">i=12</Alias>
    <Alias Alias="ByteString">i=15</Alias>
    <Alias Alias="Guid">i=14</Alias>
    <Alias Alias="XmlElement">i=16</Alias>
    <Alias Alias="NodeId">i=17</Alias>
    <Alias Alias="ExpandedNodeId">i=18</Alias>
    <Alias Alias="QualifiedName">i=20</Alias>
    <Alias Alias="LocalizedText">i=21</Alias>
    <Alias Alias="StatusCode">i=19</Alias>
    <Alias Alias="Structure">i=22</Alias>
    <Alias Alias="Number">i=26</Alias>
    <Alias Alias="Integer">i=27</Alias>
    <Alias Alias="UInteger">i=28</Alias>
    <Alias Alias="HasComponent">i=47</Alias>
    <Alias Alias="HasProperty">i=46</Alias>
    <Alias Alias="Organizes">i=35</Alias>
    <Alias Alias="HasEventSource">i=36</Alias>
    <Alias Alias="HasNotifier">i=48</Alias>
    <Alias Alias="HasSubtype">i=45</Alias>
    <Alias Alias="HasTypeDefinition">i=40</Alias>
    <Alias Alias="HasModellingRule">i=37</Alias>
    <Alias Alias="HasEncoding">i=38</Alias>
    <Alias Alias="HasDescription">i=39</Alias>
  </Aliases>
  <UAObjectType NodeId="ns=1;i=15162" BrowseName="1:MachineInfoType">
    <DisplayName>MachineInfoType</DisplayName>
    <References>
      <Reference ReferenceType="HasProperty">ns=1;i=15164</Reference>
      <Reference ReferenceType="HasProperty">ns=1;i=15048</Reference>
      <Reference ReferenceType="HasProperty">ns=1;i=15049</Reference>
      <Reference ReferenceType="HasProperty">ns=1;i=15166</Reference>
      <Reference ReferenceType="HasProperty">ns=1;i=15167</Reference>
      <Reference ReferenceType="HasSubtype" IsForward="false">i=58</Reference>
    </References>
  </UAObjectType>
  <UAVariable NodeId="ns=1;i=15164" BrowseName="1:MachineName" ParentNodeId="ns=1;i=15162" DataType="String">
    <DisplayName>MachineName</DisplayName>
    <References>
      <Reference ReferenceType="HasTypeDefinition">i=68</Reference>
      <Reference ReferenceType="HasModellingRule">i=78</Reference>
      <Reference ReferenceType="HasProperty" IsForward="false">ns=1;i=15162</Reference>
    </References>
  </UAVariable>
  <UAVariable NodeId="ns=1;i=15048" BrowseName="1:Manufacturer" ParentNodeId="ns=1;i=15162" DataType="String">
    <DisplayName>Manufacturer</DisplayName>
    <References>
      <Reference ReferenceType="HasTypeDefinition">i=68</Reference>
      <Reference ReferenceType="HasModellingRule">i=78</Reference>
      <Reference ReferenceType="HasProperty" IsForward="false">ns=1;i=15162</Reference>
    </References>
  </UAVariable>
  <UAVariable NodeId="ns=1;i=15049" BrowseName="1:SerialNumber" ParentNodeId="ns=1;i=15162" DataType="String">
    <DisplayName>SerialNumber</DisplayName>
    <References>
      <Reference ReferenceType="HasTypeDefinition">i=68</Reference>
      <Reference ReferenceType="HasModellingRule">i=78</Reference>
      <Reference ReferenceType="HasProperty" IsForward="false">ns=1;i=15162</Reference>
    </References>
  </UAVariable>
  <UAVariable NodeId="ns=1;i=15166" BrowseName="1:IsProducing" ParentNodeId="ns=1;i=15162" DataType="Boolean" AccessLevel="3">
    <DisplayName>IsProducing</DisplayName>
    <References>
      <Reference ReferenceType="HasTypeDefinition">i=68</Reference>
      <Reference ReferenceType="HasModellingRule">i=78</Reference>
      <Reference ReferenceType="HasProperty" IsForward="false">ns=1;i=15162</Reference>
    </References>
  </UAVariable>
  <UAVariable NodeId="ns=1;i=15167" BrowseName="1:MachineState" ParentNodeId="ns=1;i=15162" DataType="UInt32" AccessLevel="3">
    <DisplayName>MachineState</DisplayName>
    <References>
      <Reference ReferenceType="HasTypeDefinition">i=68</Reference>
      <Reference ReferenceType="HasModellingRule">i=78</Reference>
      <Reference ReferenceType="HasProperty" IsForward="false">ns=1;i=15162</Reference>
    </References>
  </UAVariable>
  <UAObjectType NodeId="ns=1;i=15003" BrowseName="1:GenericControllerType">
    <DisplayName>GenericControllerType</DisplayName>
    <References>
      <Reference ReferenceType="HasComponent">ns=1;i=15006</Reference>
      <Reference ReferenceType="HasComponent">ns=1;i=15012</Reference>
      <Reference ReferenceType="HasSubtype" IsForward="false">i=58</Reference>
    </References>
  </UAObjectType>
  <UAVariable NodeId="ns=1;i=15006" BrowseName="1:SetPoint" ParentNodeId="ns=1;i=15003" DataType="Double" AccessLevel="3">
    <DisplayName>SetPoint</DisplayName>
    <References>
      <Reference ReferenceType="HasProperty">ns=1;i=15010</Reference>
      <Reference ReferenceType="HasTypeDefinition">i=2368</Reference>
      <Reference ReferenceType="HasModellingRule">i=78</Reference>
      <Reference ReferenceType="HasComponent" IsForward="false">ns=1;i=15003</Reference>
    </References>
  </UAVariable>
  <UAVariable NodeId="ns=1;i=15010" BrowseName="EURange" ParentNodeId="ns=1;i=15006" DataType="i=884">
    <DisplayName>EURange</DisplayName>
    <References>
      <Reference ReferenceType="HasTypeDefinition">i=68</Reference>
      <Reference ReferenceType="HasModellingRule">i=78</Reference>
      <Reference ReferenceType="HasProperty" IsForward="false">ns=1;i=15006</Reference>
    </References>
  </UAVariable>
  <UAVariable NodeId="ns=1;i=15012" BrowseName="1:Measurement" ParentNodeId="ns=1;i=15003" DataType="Double">
    <DisplayName>Measurement</DisplayName>
    <References>
      <Reference ReferenceType="HasProperty">ns=1;i=15016</Reference>
      <Reference ReferenceType="HasTypeDefinition">i=2368</Reference>
      <Reference ReferenceType="HasModellingRule">i=78</Reference>
      <Reference ReferenceType="HasComponent" IsForward="false">ns=1;i=15003</Reference>
    </References>
  </UAVariable>
  <UAVariable NodeId="ns=1;i=15016" BrowseName="EURange" ParentNodeId="ns=1;i=15012" DataType="i=884">
    <DisplayName>EURange</DisplayName>
    <References>
      <Reference ReferenceType="HasTypeDefinition">i=68</Reference>
      <Reference ReferenceType="HasModellingRule">i=78</Reference>
      <Reference ReferenceType="HasProperty" IsForward="false">ns=1;i=15012</Reference>
    </References>
  </UAVariable>
  <UAObjectType NodeId="ns=1;i=15018" BrowseName="1:FlowControllerType">
    <DisplayName>FlowControllerType</DisplayName>
    <References>
      <Reference ReferenceType="HasSubtype" IsForward="false">ns=1;i=15003</Reference>
    </References>
  </UAObjectType>
  <UAObjectType NodeId="ns=1;i=15033" BrowseName="1:LevelControllerType">
    <DisplayName>LevelControllerType</DisplayName>
    <References>
      <Reference ReferenceType="HasSubtype" IsForward="false">ns=1;i=15003</Reference>
    </References>
  </UAObjectType>
  <UAObjectType NodeId="ns=1;i=15050" BrowseName="1:TemperatureControllerType">
    <DisplayName>TemperatureControllerType</DisplayName>
    <References>
      <Reference ReferenceType="HasSubtype" IsForward="false">ns=1;i=15003</Reference>
    </References>
  </UAObjectType>
  <UAObjectType NodeId="ns=1;i=15097" BrowseName="1:MachineType">
    <DisplayName>MachineType</DisplayName>
    <References>
      <Reference ReferenceType="HasComponent">ns=1;i=15098</Reference>
      <Reference ReferenceType="HasComponent">ns=1;i=15065</Reference>
      <Reference ReferenceType="HasComponent">ns=1;i=15078</Reference>
      <Reference ReferenceType="HasComponent">ns=1;i=15091</Reference>
      <Reference ReferenceType="HasSubtype" IsForward="false">i=58</Reference>
    </References>
  </UAObjectType>
  <UAObject NodeId="ns=1;i=15098" BrowseName="1:MachineInfo" ParentNodeId="ns=1;i=15097">
    <DisplayName>MachineInfo</DisplayName>
    <References>
      <Reference ReferenceType="HasProperty">ns=1;i=15099</Reference>
      <Reference ReferenceType="HasProperty">ns=1;i=15063</Reference>
      <Reference ReferenceType="HasProperty">ns=1;i=15064</Reference>
      <Reference ReferenceType="HasProperty">ns=1;i=15100</Reference>
      <Reference ReferenceType="HasProperty">ns=1;i=15101</Reference>
      <Reference ReferenceType="HasTypeDefinition">ns=1;i=15162</Reference>
      <Reference ReferenceType="HasModellingRule">i=78</Reference>
      <Reference ReferenceType="HasComponent" IsForward="false">ns=1;i=15097</Reference>
    </References>
  </UAObject>
  <UAVariable NodeId="ns=1;i=15099" BrowseName="1:MachineName" ParentNodeId="ns=1;i=15098" DataType="String">
    <DisplayName>MachineName</DisplayName>
    <References>
      <Reference ReferenceType="HasTypeDefinition">i=68</Reference>
      <Reference ReferenceType="HasModellingRule">i=78</Reference>
      <Reference ReferenceType="HasProperty" IsForward="false">ns=1;i=15098</Reference>
    </References>
  </UAVariable>
  <UAVariable NodeId="ns=1;i=15063" BrowseName="1:Manufacturer" ParentNodeId="ns=1;i=15098" DataType="String">
    <DisplayName>Manufacturer</DisplayName>
    <References>
      <Reference ReferenceType="HasTypeDefinition">i=68</Reference>
      <Reference ReferenceType="HasModellingRule">i=78</Reference>
      <Reference ReferenceType="HasProperty" IsForward="false">ns=1;i=15098</Reference>
    </References>
  </UAVariable>
  <UAVariable NodeId="ns=1;i=15064" BrowseName="1:SerialNumber" ParentNodeId="ns=1;i=15098" DataType="String">
    <DisplayName>SerialNumber</DisplayName>
    <References>
      <Reference ReferenceType="HasTypeDefinition">i=68</Reference>
      <Reference ReferenceType="HasModellingRule">i=78</Reference>
      <Reference ReferenceType="HasProperty" IsForward="false">ns=1;i=15098</Reference>
    </References>
  </UAVariable>
  <UAVariable NodeId="ns=1;i=15100" BrowseName="1:IsProducing" ParentNodeId="ns=1;i=15098" DataType="Boolean" AccessLevel="3">
    <DisplayName>IsProducing</DisplayName>
    <References>
      <Reference ReferenceType="HasTypeDefinition">i=68</Reference>
      <Reference ReferenceType="HasModellingRule">i=78</Reference>
      <Reference ReferenceType="HasProperty" IsForward="false">ns=1;i=15098</Reference>
    </References>
  </UAVariable>
  <UAVariable NodeId="ns=1;i=15101" BrowseName="1:MachineState" ParentNodeId="ns=1;i=15098" DataType="UInt32" AccessLevel="3">
    <DisplayName>MachineState</DisplayName>
    <References>
      <Reference ReferenceType="HasTypeDefinition">i=68</Reference>
      <Reference ReferenceType="HasModellingRule">i=78</Reference>
      <Reference ReferenceType="HasProperty" IsForward="false">ns=1;i=15098</Reference>
    </References>
  </UAVariable>
  <UAObject NodeId="ns=1;i=15065" BrowseName="1:Temperature" ParentNodeId="ns=1;i=15097">
    <DisplayName>Temperature</DisplayName>
    <References>
      <Reference ReferenceType="HasComponent">ns=1;i=15066</Reference>
      <Reference ReferenceType="HasComponent">ns=1;i=15072</Reference>
      <Reference ReferenceType="HasTypeDefinition">ns=1;i=15050</Reference>
      <Reference ReferenceType="HasModellingRule">i=78</Reference>
      <Reference ReferenceType="HasComponent" IsForward="false">ns=1;i=15097</Reference>
    </References>
  </UAObject>
  <UAVariable NodeId="ns=1;i=15066" BrowseName="1:SetPoint" ParentNodeId="ns=1;i=15065" DataType="Double" AccessLevel="3">
    <DisplayName>SetPoint</DisplayName>
    <References>
      <Reference ReferenceType="HasProperty">ns=1;i=15070</Reference>
      <Reference ReferenceType="HasTypeDefinition">i=2368</Reference>
      <Reference ReferenceType="HasModellingRule">i=78</Reference>
      <Reference ReferenceType="HasComponent" IsForward="false">ns=1;i=15065</Reference>
    </References>
  </UAVariable>
  <UAVariable NodeId="ns=1;i=15070" BrowseName="EURange" ParentNodeId="ns=1;i=15066" DataType="i=884">
    <DisplayName>EURange</DisplayName>
    <References>
      <Reference ReferenceType="HasTypeDefinition">i=68</Reference>
      <Reference ReferenceType="HasModellingRule">i=78</Reference>
      <Reference ReferenceType="HasProperty" IsForward="false">ns=1;i=15066</Reference>
    </References>
  </UAVariable>
  <UAVariable NodeId="ns=1;i=15072" BrowseName="1:Measurement" ParentNodeId="ns=1;i=15065" DataType="Double">
    <DisplayName>Measurement</DisplayName>
    <References>
      <Reference ReferenceType="HasProperty">ns=1;i=15076</Reference>
      <Reference ReferenceType="HasTypeDefinition">i=2368</Reference>
      <Reference ReferenceType="HasModellingRule">i=78</Reference>
      <Reference ReferenceType="HasComponent" IsForward="false">ns=1;i=15065</Reference>
    </References>
  </UAVariable>
  <UAVariable NodeId="ns=1;i=15076" BrowseName="EURange" ParentNodeId="ns=1;i=15072" DataType="i=884">
    <DisplayName>EURange</DisplayName>
    <References>
      <Reference ReferenceType="HasTypeDefinition">i=68</Reference>
      <Reference ReferenceType="HasModellingRule">i=78</Reference>
      <Reference ReferenceType="HasProperty" IsForward="false">ns=1;i=15072</Reference>
    </References>
  </UAVariable>
  <UAObject NodeId="ns=1;i=15078" BrowseName="1:Flow" ParentNodeId="ns=1;i=15097">
    <DisplayName>Flow</DisplayName>
    <References>
      <Reference ReferenceType="HasComponent">ns=1;i=15079</Reference>
      <Reference ReferenceType="HasComponent">ns=1;i=15085</Reference>
      <Reference ReferenceType="HasTypeDefinition">ns=1;i=15018</Reference>
      <Reference ReferenceType="HasModellingRule">i=78</Reference>
      <Reference ReferenceType="HasComponent" IsForward="false">ns=1;i=15097</Reference>
    </References>
  </UAObject>
  <UAVariable NodeId="ns=1;i=15079" BrowseName="1:SetPoint" ParentNodeId="ns=1;i=15078" DataType="Double" AccessLevel="3">
    <DisplayName>SetPoint</DisplayName>
    <References>
      <Reference ReferenceType="HasProperty">ns=1;i=15083</Reference>
      <Reference ReferenceType="HasTypeDefinition">i=2368</Reference>
      <Reference ReferenceType="HasModellingRule">i=78</Reference>
      <Reference ReferenceType="HasComponent" IsForward="false">ns=1;i=15078</Reference>
    </References>
  </UAVariable>
  <UAVariable NodeId="ns=1;i=15083" BrowseName="EURange" ParentNodeId="ns=1;i=15079" DataType="i=884">
    <DisplayName>EURange</DisplayName>
    <References>
      <Reference ReferenceType="HasTypeDefinition">i=68</Reference>
      <Reference ReferenceType="HasModellingRule">i=78</Reference>
      <Reference ReferenceType="HasProperty" IsForward="false">ns=1;i=15079</Reference>
    </References>
  </UAVariable>
  <UAVariable NodeId="ns=1;i=15085" BrowseName="1:Measurement" ParentNodeId="ns=1;i=15078" DataType="Double">
    <DisplayName>Measurement</DisplayName>
    <References>
      <Reference ReferenceType="HasProperty">ns=1;i=15089</Reference>
      <Reference ReferenceType="HasTypeDefinition">i=2368</Reference>
      <Reference ReferenceType="HasModellingRule">i=78</Reference>
      <Reference ReferenceType="HasComponent" IsForward="false">ns=1;i=15078</Reference>
    </References>
  </UAVariable>
  <UAVariable NodeId="ns=1;i=15089" BrowseName="EURange" ParentNodeId="ns=1;i=15085" DataType="i=884">
    <DisplayName>EURange</DisplayName>
    <References>
      <Reference ReferenceType="HasTypeDefinition">i=68</Reference>
      <Reference ReferenceType="HasModellingRule">i=78</Reference>
      <Reference ReferenceType="HasProperty" IsForward="false">ns=1;i=15085</Reference>
    </References>
  </UAVariable>
  <UAObject NodeId="ns=1;i=15091" BrowseName="1:Level" ParentNodeId="ns=1;i=15097">
    <DisplayName>Level</DisplayName>
    <References>
      <Reference ReferenceType="HasComponent">ns=1;i=15092</Reference>
      <Reference ReferenceType="HasComponent">ns=1;i=15151</Reference>
      <Reference ReferenceType="HasTypeDefinition">ns=1;i=15033</Reference>
      <Reference ReferenceType="HasModellingRule">i=78</Reference>
      <Reference ReferenceType="HasComponent" IsForward="false">ns=1;i=15097</Reference>
    </References>
  </UAObject>
  <UAVariable NodeId="ns=1;i=15092" BrowseName="1:SetPoint" ParentNodeId="ns=1;i=15091" DataType="Double" AccessLevel="3">
    <DisplayName>SetPoint</DisplayName>
    <References>
      <Reference ReferenceType="HasProperty">ns=1;i=15096</Reference>
      <Reference ReferenceType="HasTypeDefinition">i=2368</Reference>
      <Reference ReferenceType="HasModellingRule">i=78</Reference>
      <Reference ReferenceType="HasComponent" IsForward="false">ns=1;i=15091</Reference>
    </References>
  </UAVariable>
  <UAVariable NodeId="ns=1;i=15096" BrowseName="EURange" ParentNodeId="ns=1;i=15092" DataType="i=884">
    <DisplayName>EURange</DisplayName>
    <References>
      <Reference ReferenceType="HasTypeDefinition">i=68</Reference>
      <Reference ReferenceType="HasModellingRule">i=78</Reference>
      <Reference ReferenceType="HasProperty" IsForward="false">ns=1;i=15092</Reference>
    </References>
  </UAVariable>
  <UAVariable NodeId="ns=1;i=15151" BrowseName="1:Measurement" ParentNodeId="ns=1;i=15091" DataType="Double">
    <DisplayName>Measurement</DisplayName>
    <References>
      <Reference ReferenceType="HasProperty">ns=1;i=15155</Reference>
      <Reference ReferenceType="HasTypeDefinition">i=2368</Reference>
      <Reference ReferenceType="HasModellingRule">i=78</Reference>
      <Reference ReferenceType="HasComponent" IsForward="false">ns=1;i=15091</Reference>
    </References>
  </UAVariable>
  <UAVariable NodeId="ns=1;i=15155" BrowseName="EURange" ParentNodeId="ns=1;i=15151" DataType="i=884">
    <DisplayName>EURange</DisplayName>
    <References>
      <Reference ReferenceType="HasTypeDefinition">i=68</Reference>
      <Reference ReferenceType="HasModellingRule">i=78</Reference>
      <Reference ReferenceType="HasProperty" IsForward="false">ns=1;i=15151</Reference>
    </References>
  </UAVariable>
  <UAView NodeId="ns=1;i=15001" BrowseName="1:Engineering">
    <DisplayName>Engineering</DisplayName>
    <References>
      <Reference ReferenceType="Organizes" IsForward="false">i=87</Reference>
    </References>
  </UAView>
  <UAView NodeId="ns=1;i=15002" BrowseName="1:Operations">
    <DisplayName>Operations</DisplayName>
    <References>
      <Reference ReferenceType="Organizes" IsForward="false">i=87</Reference>
    </References>
  </UAView>
</UANodeSet>